[{"title": "Programator Python (Rom\u00e2nia)", "company_name": "ASSIST", "salary": "\u0414\u043e\u0433\u043e\u0432\u043e\u0440\u043d\u0430\u044f", "location": "\u041a\u0438\u0448\u0438\u043d\u0435\u0432"}, {"title": "Python Developer (Romania)", "company_name": "ASSIST", "salary": "\u0414\u043e\u0433\u043e\u0432\u043e\u0440\u043d\u0430\u044f", "location": "\u041a\u0438\u0448\u0438\u043d\u0435\u0432"}, {"title": "Python Developer", "company_name": "EBS INTEGRATOR", "salary": "\u0414\u043e\u0433\u043e\u0432\u043e\u0440\u043d\u0430\u044f", "location": "\u041a\u0438\u0448\u0438\u043d\u0435\u0432"}, {"title": "Python Developer", "company_name": "EnergyMarketPrice", "salary": "\u0414\u043e\u0433\u043e\u0432\u043e\u0440\u043d\u0430\u044f", "location": "\u041a\u0438\u0448\u0438\u043d\u0435\u0432"}, {"title": "Middle Python Developer", "company_name": "Simpals", "salary": "\u0414\u043e\u0433\u043e\u0432\u043e\u0440\u043d\u0430\u044f", "location": "\u041a\u0438\u0448\u0438\u043d\u0435\u0432"}, {"title": "Middle Python Developer", "company_name": "Simpals", "salary": "\u0414\u043e\u0433\u043e\u0432\u043e\u0440\u043d\u0430\u044f", "location": "\u041a\u0438\u0448\u0438\u043d\u0435\u0432"}, {"title": "Python Developer", "company_name": "Amdaris", "salary": "\u0414\u043e\u0433\u043e\u0432\u043e\u0440\u043d\u0430\u044f", "location": "\u041a\u0438\u0448\u0438\u043d\u0435\u0432"}, {"title": "Python Developer", "company_name": "Indrivo", "salary": "\u0414\u043e\u0433\u043e\u0432\u043e\u0440\u043d\u0430\u044f", "location": "\u041a\u0438\u0448\u0438\u043d\u0435\u0432"}, {"title": "Python Developer", "company_name": "Pentalog", "salary": "\u0414\u043e\u0433\u043e\u0432\u043e\u0440\u043d\u0430\u044f", "location": "\u041a\u0438\u0448\u0438\u043d\u0435\u0432"}, {"title": "DevOps Engineer (WINIFY)", "company_name": "Mantis", "salary": "\u0414\u043e\u0433\u043e\u0432\u043e\u0440\u043d\u0430\u044f", "location": "\u041a\u0438\u0448\u0438\u043d\u0435\u0432"}, {"title": "System engineer, L2 Support (full-time, evening shift, remote)", "company_name": "Mantis", "salary": "\u0414\u043e\u0433\u043e\u0432\u043e\u0440\u043d\u0430\u044f", "location": "\u041a\u0438\u0448\u0438\u043d\u0435\u0432"}, {"title": "\u0421\u0438\u0441\u0442\u0435\u043c\u043d\u044b\u0439 \u0418\u043d\u0436\u0435\u043d\u0435\u0440 - L2 Support (full-time, evening shift,...", "company_name": "Mantis", "salary": "\u0414\u043e\u0433\u043e\u0432\u043e\u0440\u043d\u0430\u044f", "location": "\u041a\u0438\u0448\u0438\u043d\u0435\u0432"}, {"title": "Economist principal pe perioad\u0103 determinat\u0103 responsabil...", "company_name": "Banca Na\u021bional\u0103 a Moldovei", "salary": "\u0414\u043e\u0433\u043e\u0432\u043e\u0440\u043d\u0430\u044f", "location": "\u041a\u0438\u0448\u0438\u043d\u0435\u0432"}, {"title": "Big Data Engineer", "company_name": "Search4staff.com HR-Consulting", "salary": "\u0414\u043e\u0433\u043e\u0432\u043e\u0440\u043d\u0430\u044f", "location": "\u041a\u0438\u0448\u0438\u043d\u0435\u0432"}, {"title": "QA Automation Developer", "company_name": "Search4staff.com HR-Consulting", "salary": "\u0414\u043e\u0433\u043e\u0432\u043e\u0440\u043d\u0430\u044f", "location": "\u041a\u0438\u0448\u0438\u043d\u0435\u0432"}, {"title": "Inginer DevOps pentru Rom\u00e2nia", "company_name": "ASSIST", "salary": "\u0414\u043e\u0433\u043e\u0432\u043e\u0440\u043d\u0430\u044f", "location": "\u041a\u0438\u0448\u0438\u043d\u0435\u0432"}, {"title": "Javascript Developer (Romania)", "company_name": "ASSIST", "salary": "\u0414\u043e\u0433\u043e\u0432\u043e\u0440\u043d\u0430\u044f", "location": "\u041a\u0438\u0448\u0438\u043d\u0435\u0432"}, {"title": "Android \u0440\u0430\u0437\u0440\u0430\u0431\u043e\u0442\u0447\u0438\u043a", "company_name": "MUSQOGEE", "salary": "\u0414\u043e\u0433\u043e\u0432\u043e\u0440\u043d\u0430\u044f", "location": "\u041a\u0438\u0448\u0438\u043d\u0435\u0432"}, {"title": "Middle / Senior Fullstack Developer (Java+Angular)", "company_name": "Feel IT Services", "salary": "\u0414\u043e\u0433\u043e\u0432\u043e\u0440\u043d\u0430\u044f", "location": "\u041a\u0438\u0448\u0438\u043d\u0435\u0432"}, {"title": "Junior DevOps Engineer", "company_name": "EBS INTEGRATOR", "salary": "\u0414\u043e\u0433\u043e\u0432\u043e\u0440\u043d\u0430\u044f", "location": "\u041a\u0438\u0448\u0438\u043d\u0435\u0432"}, {"title": "Senior Back-End Engineer", "company_name": "Digital MR", "salary": "\u0414\u043e\u0433\u043e\u0432\u043e\u0440\u043d\u0430\u044f", "location": "\u041a\u0438\u0448\u0438\u043d\u0435\u0432"}, {"title": "Senior .Net Developers", "company_name": "Jivy Group", "salary": "\u0414\u043e\u0433\u043e\u0432\u043e\u0440\u043d\u0430\u044f", "location": "\u041a\u0438\u0448\u0438\u043d\u0435\u0432"}, {"title": "C++ Developer", "company_name": "Noction", "salary": "\u0414\u043e\u0433\u043e\u0432\u043e\u0440\u043d\u0430\u044f", "location": "\u041a\u0438\u0448\u0438\u043d\u0435\u0432"}, {"title": "QA Automation Engineer (874)", "company_name": "Gilat Satellite Networks Ltd", "salary": "\u0414\u043e\u0433\u043e\u0432\u043e\u0440\u043d\u0430\u044f", "location": "\u041a\u0438\u0448\u0438\u043d\u0435\u0432"}, {"title": "Inginer de system software, Sec\u021bia programe \u0219i implementare,...", "company_name": "Moldindconbank", "salary": "\u0414\u043e\u0433\u043e\u0432\u043e\u0440\u043d\u0430\u044f", "location": "\u041a\u0438\u0448\u0438\u043d\u0435\u0432"}, {"title": "PHP Team Leader", "company_name": "Indrivo", "salary": "\u0414\u043e\u0433\u043e\u0432\u043e\u0440\u043d\u0430\u044f", "location": "\u041a\u0438\u0448\u0438\u043d\u0435\u0432"}, {"title": "QA Automation Engineer", "company_name": "Orange Moldova", "salary": "\u0414\u043e\u0433\u043e\u0432\u043e\u0440\u043d\u0430\u044f", "location": "\u041a\u0438\u0448\u0438\u043d\u0435\u0432"}, {"title": "Senior DevOps", "company_name": "Titanium.Codes", "salary": "\u0414\u043e\u0433\u043e\u0432\u043e\u0440\u043d\u0430\u044f", "location": "\u041a\u0438\u0448\u0438\u043d\u0435\u0432"}, {"title": "Big Data Engineer", "company_name": "Orange Moldova", "salary": "\u0414\u043e\u0433\u043e\u0432\u043e\u0440\u043d\u0430\u044f", "location": "\u041a\u0438\u0448\u0438\u043d\u0435\u0432"}, {"title": "Front-end Developer (ReactJS)", "company_name": "Allied Testing", "salary": "\u0414\u043e\u0433\u043e\u0432\u043e\u0440\u043d\u0430\u044f", "location": "\u041a\u0438\u0448\u0438\u043d\u0435\u0432"}, {"title": "Senior test automation engineer", "company_name": "Allied Testing", "salary": "\u0414\u043e\u0433\u043e\u0432\u043e\u0440\u043d\u0430\u044f", "location": "\u041a\u0438\u0448\u0438\u043d\u0435\u0432"}, {"title": "Internship Program in Applications Management DevOps Engineer", "company_name": "Endava", "salary": "\u0414\u043e\u0433\u043e\u0432\u043e\u0440\u043d\u0430\u044f", "location": "\u041a\u0438\u0448\u0438\u043d\u0435\u0432"}, {"title": "Senior QAA Automation - Iasi, Romania", "company_name": "Ness", "salary": "\u0414\u043e\u0433\u043e\u0432\u043e\u0440\u043d\u0430\u044f", "location": "\u041a\u0438\u0448\u0438\u043d\u0435\u0432"}, {"title": "Senior DevOps Engineer", "company_name": "Endava", "salary": "\u0414\u043e\u0433\u043e\u0432\u043e\u0440\u043d\u0430\u044f", "location": "\u041a\u0438\u0448\u0438\u043d\u0435\u0432"}, {"title": "DevOps Engineer", "company_name": "Code Factory", "salary": "\u0414\u043e\u0433\u043e\u0432\u043e\u0440\u043d\u0430\u044f", "location": "\u041a\u0438\u0448\u0438\u043d\u0435\u0432"}, {"title": "Senior python developer", "company_name": "", "salary": "1500-3000 USD", "location": "\u041a\u0438\u0448\u0438\u043d\u0435\u0432"}, {"title": "Python developer (web-backend / system) - rem...", "company_name": "Smartsoftdev SRL", "salary": "\u041f\u043e \u0434\u043e\u0433\u043e\u0432\u043e\u0440\u0451\u043d\u043d\u043e\u0441\u0442\u0438", "location": "\u041a\u0438\u0448\u0438\u043d\u0435\u0432"}, {"title": "\u041f\u0440\u043e\u0433\u0440\u0430\u043c\u043c\u0438\u0441\u0442 Python", "company_name": "Total Sistem SRL", "salary": "\u041f\u043e \u0434\u043e\u0433\u043e\u0432\u043e\u0440\u0451\u043d\u043d\u043e\u0441\u0442\u0438", "location": "\u041a\u0438\u0448\u0438\u043d\u0435\u0432"}, {"title": "Python developer", "company_name": "Darqube", "salary": "\u041f\u043e \u0434\u043e\u0433\u043e\u0432\u043e\u0440\u0451\u043d\u043d\u043e\u0441\u0442\u0438", "location": "\u041a\u0438\u0448\u0438\u043d\u0435\u0432"}, {"title": "\u041f\u0440\u0435\u043f\u043e\u0434\u0430\u0432\u0430\u0442\u0435\u043b\u044c \u043a\u0443\u0440\u0441\u043e\u0432 \u043f\u043e \u044f\u0437\u044b\u043a\u0430\u043c \u043f\u0440\u043e\u0433\u0440\u0430\u043c\u043c\u0438\u0440\u043e\u0432\u0430\u043d...", "company_name": "\u0423\u0447\u0435\u0431\u043d\u044b\u0439 \u0446\u0435\u043d\u0442\u0440 VanAr", "salary": "\u041f\u043e \u0434\u043e\u0433\u043e\u0432\u043e\u0440\u0451\u043d\u043d\u043e\u0441\u0442\u0438", "location": "\u041a\u0438\u0448\u0438\u043d\u0435\u0432"}, {"title": "\u041f\u0440\u043e\u0433\u0440\u0430\u043c\u043c\u0438\u0441\u0442 Python", "company_name": "ALSODEV", "salary": "5000-20000 MDL", "location": "\u041a\u0438\u0448\u0438\u043d\u0435\u0432"}, {"title": "\u0420\u0430\u0437\u0440\u0430\u0431\u043e\u0442\u0447\u0438\u043a Python", "company_name": "Seagull Way inc.", "salary": "800-1500 USD", "location": "\u041a\u0438\u0448\u0438\u043d\u0435\u0432"}]